<?xml version="1.0" encoding="UTF-8"?>
<metadata xml:lang="en"><Esri><CreaDate>20200303</CreaDate><CreaTime>23303600</CreaTime><ArcGISFormat>1.0</ArcGISFormat><SyncOnce>TRUE</SyncOnce><DataProperties><lineage><Process Name="Build Raster Attribute Table" ToolSource="c:\program files (x86)\arcgis\desktop10.2\ArcToolbox\Toolboxes\Data Management Tools.tbx\BuildRasterAttributeTable" Date="20200303" Time="233036">BuildRasterAttributeTable "D:\0000000000.new analysis. luhrcp.models\0.000000repeat again with proper reg\rcp4.5models\MPi_ESM_LR\results\restrict\cov_all.34.asc" NONE</Process></lineage></DataProperties></Esri></metadata>
